concurrent_tasking/__init__.py
concurrent_tasking/models.py
concurrent_tasking/task_manager.py
concurrent_tasking/utils.py
ConcurrentTasking-0.2.0.dist-info/LICENSE
ConcurrentTasking-0.2.0.dist-info/METADATA
ConcurrentTasking-0.2.0.dist-info/WHEEL
ConcurrentTasking-0.2.0.dist-info/top_level.txt
ConcurrentTasking-0.2.0.dist-info/RECORD
