Metadata-Version: 2.1
Name: ConcurrentTasking
Version: 0.2.0
Summary: A powerful, yet straightforward library for managing and processing tasks concurrently.
Author-email: Tom Samwel <tommiesamwel@gmail.com>
Classifier: Programming Language :: Python :: 3
Classifier: License :: OSI Approved :: MIT License
Classifier: Operating System :: OS Independent
Requires-Python: >=3.7
License-File: LICENSE
Requires-Dist: pydantic >=1.8.2
